pyrebase/__init__.py
pyrebase/pyrebase.py
sseclient/__init__.py
sseclient/sseclient.py
pyrebase5-5.0.1.dist-info/METADATA
pyrebase5-5.0.1.dist-info/WHEEL
pyrebase5-5.0.1.dist-info/top_level.txt
pyrebase5-5.0.1.dist-info/RECORD
